LICENSE
MANIFEST.in
README.md
pyproject.toml
setup.py
bfit/__init__.py
bfit/__main__.py
bfit/global_variables.py
bfit.egg-info/PKG-INFO
bfit.egg-info/SOURCES.txt
bfit.egg-info/dependency_links.txt
bfit.egg-info/entry_points.txt
bfit.egg-info/requires.txt
bfit.egg-info/top_level.txt
bfit/backend/FunctionPlacer.py
bfit/backend/ParameterFunction.py
bfit/backend/PltTracker.py
bfit/backend/__init__.py
bfit/backend/colors.py
bfit/backend/entry_color_set.py
bfit/backend/fitdata.py
bfit/backend/get_derror.py
bfit/backend/raise_window.py
bfit/data/icon.gif
bfit/data/nmr_antenna_data.csv
bfit/fitting/__init__.py
bfit/fitting/decay_31mg.py
bfit/fitting/fit_bdata.py
bfit/fitting/fitter.py
bfit/fitting/fitter_curve_fit.py
bfit/fitting/fitter_migrad_hesse.py
bfit/fitting/fitter_migrad_minos.py
bfit/fitting/functions.py
bfit/fitting/gen_init_par.py
bfit/fitting/global_bdata_fitter.py
bfit/fitting/global_fitter.py
bfit/fitting/integrator.cpp
bfit/fitting/integrator.pyx
bfit/fitting/leastsquares.py
bfit/fitting/minuit.py
bfit/fitting/FastNumericalIntegration_src/DEIntegrationConstants.h
bfit/fitting/FastNumericalIntegration_src/DEIntegrator.h
bfit/fitting/FastNumericalIntegration_src/integration_fns.cpp
bfit/fitting/FastNumericalIntegration_src/integration_fns.h
bfit/gui/InputLine.py
bfit/gui/__init__.py
bfit/gui/bfit.py
bfit/gui/calculator_nmr_B1.py
bfit/gui/calculator_nmr_atten.py
bfit/gui/calculator_nqr_B0.py
bfit/gui/calculator_nqr_B0_hh6.py
bfit/gui/dataline.py
bfit/gui/fitline.py
bfit/gui/popup_add_param.py
bfit/gui/popup_deadtime.py
bfit/gui/popup_drawstyle.py
bfit/gui/popup_fit_constraints.py
bfit/gui/popup_fit_results.py
bfit/gui/popup_ongoing_process.py
bfit/gui/popup_param.py
bfit/gui/popup_prepare_data.py
bfit/gui/popup_redraw_period.py
bfit/gui/popup_set_histograms.py
bfit/gui/popup_set_ppm_reference.py
bfit/gui/popup_show_param.py
bfit/gui/popup_terminal.py
bfit/gui/popup_units.py
bfit/gui/tab_fetch_files.py
bfit/gui/tab_fileviewer.py
bfit/gui/tab_fit_files.py
bfit/gui/template_fit_popup.py
bfit/test/__init__.py
bfit/test/test_calculator_nmr_B1.py
bfit/test/test_calculator_nmr_atten.py
bfit/test/test_calculator_nqr_B0.py
