Metadata-Version: 2.1
Name: bfit
Version: 4.20.4
Summary: β-NMR and β-NQR Data Analysis
Home-page: https://github.com/dfujim/bfit
Author: Derek Fujimoto
Author-email: dfujimoto@triumf.ca
License: UNKNOWN
Platform: UNKNOWN
Classifier: Programming Language :: Python :: 3
Classifier: Programming Language :: Python :: 3.6
Classifier: Programming Language :: Python :: 3.8
Classifier: Programming Language :: Cython
Classifier: License :: OSI Approved :: GNU Lesser General Public License v3 (LGPLv3)
Classifier: Operating System :: POSIX :: Linux
Classifier: Operating System :: MacOS
Classifier: Development Status :: 5 - Production/Stable
License-File: LICENSE
